west_ic_antenna/__init__.py
west_ic_antenna/antenna.py
west_ic_antenna/digital_twin.py
west_ic_antenna/topica.py
west_ic_antenna/data/Sparameters/front_faces/PetraM/convert_to_s4p.py
west_ic_antenna/test/__init__.py
west_ic_antenna/test/test_antenna.py
west_ic_antenna-0.14.0.dist-info/LICENSE
west_ic_antenna-0.14.0.dist-info/METADATA
west_ic_antenna-0.14.0.dist-info/WHEEL
west_ic_antenna-0.14.0.dist-info/top_level.txt
west_ic_antenna-0.14.0.dist-info/RECORD
