Metadata-Version: 2.1
Name: west-ic-antenna
Version: 0.14.0
Summary: WEST ICRH Antenna Electrical Model
License: LICENSE
Requires-Python: >=3.11
License-File: LICENSE
Requires-Dist: ipympl>=0.9.4
Requires-Dist: ipywidgets>=8.1.5
Requires-Dist: matplotlib>=3.9.2
Requires-Dist: networkx>=3.4.2
Requires-Dist: numpy>=2.1.3
Requires-Dist: scikit-rf>=1.4.1
Requires-Dist: tqdm>=4.67.0
Provides-Extra: test
Requires-Dist: pytest>=8.3.3; extra == "test"
Provides-Extra: docs
Requires-Dist: ipykernel>=6.29.5; extra == "docs"
Requires-Dist: nbsphinx>=0.9.5; extra == "docs"
Requires-Dist: pandoc>=2.4; extra == "docs"
Requires-Dist: sphinx-rtd-theme>=3.0.2; extra == "docs"
Requires-Dist: sphinx>=8.1.3; extra == "docs"
